lokal/__init__.py
lokal/lokal.py
lokal_py-0.0.1.dist-info/LICENSE
lokal_py-0.0.1.dist-info/METADATA
lokal_py-0.0.1.dist-info/WHEEL
lokal_py-0.0.1.dist-info/top_level.txt
lokal_py-0.0.1.dist-info/RECORD
